{
  "text": "euiiooaa\r\nValuation as of 28.02.2025\r\nMESSOS ENTERPRISES LTD.\r\nClient Number // 366223 Valuation currency // USD Investment profile // Undefined Risk Profile // Medium-high\r\nCorn�r Banca SA // T�distrasse 27 // Postfach 1640 // 8027 Z�rich_Switzerland // Hauptsitz Via Canova 16, 6901 Lugano_Switzerland Tel. +41 44 218 10 20 // Fax +41 44 218 10 29 // info@corner.ch // corner.ch Swift CBLUCH2280A // Clearing 8490 // CHE-105.962.409 IVA\r\n\r\n\faeouiAEOUI\r\n\r\naeouiAEOUI\r\n\r\nSummary Asset Allocation\r\nAssets and Liabilities Structure Currency allocation Performance Overview/Evolution Asset Listing Liquidity and liabilities Bonds Equities Structured products Other assets Expected Cash Flows (Overview) Glossary Notices and other information\r\n\r\nMESSOS ENTERPRISES LTD.\r\nValuation as of 28.02.2025 Client Number 366223\r\nIndex\r\n1 2 2 3 4 5 5 6 10 11 14 15 16 18\r\n\r\nCorn�r Banca SA // T�distrasse 27 // Postfach 1640 // 8027 Z�rich_Switzerland // Hauptsitz Via Canova 16, 6901 Lugano_Switzerland Tel. +41 44 218 10 20 // Fax +41 44 218 10 29 // info@corner.ch // corner.ch Swift CBLUCH2280A // Clearing 8490 // CHE-105.962.409 IVA\r\n\r\nPrint date 01.03.2025 // Page I\r\n\r\n\faeouiAEOUI\r\n\r\naeouiAEOUI\r\n\r\nOther assets\r\n\r\nStructured products\r\n\r\nEquities CHF\r\n\r\nAssets Currencies\r\n\r\nLiquidity Bonds\r\n\r\nAssets\r\nLiquidity Bonds Equities Mixed funds Structured products Precious metals Real Estate Other assets\r\nTotal Thereof accrued interest\r\nIncome\r\nCollected Accruals\r\n\r\nMESSOS ENTERPRISES LTD.\r\nValuation as of 28.02.2025 Client Number 366223\r\n\r\nSummary\r\n\r\nCountervalue USD Weight in %\r\n\r\n47'850 11'558'957\r\n27'406\r\n\r\n0.25% 59.24%\r\n0.14%\r\n\r\n7'850'257\r\n\r\n40.24%\r\n\r\n26'129 19'510'599\r\n309'516\r\nCountervalue USD 69'055\r\n309'516\r\n\r\n0.13% 100.00%\r\n\r\nCurrencies\r\nUSD CHF\r\nTotal\r\n\r\nValue Exchange Rates\r\n\r\n24'720\r\n\r\n1.1086\r\n\r\n0.9020\r\n\r\nCountervalue USD\r\n19'483'193 27'406\r\n19'510'599\r\n\r\nWeight in %\r\n99.86% 0.14%\r\n100.00%\r\n\r\nUSD\r\nNote // Blocked guarantees\r\nCorn�r Banca SA // T�distrasse 27 // Postfach 1640 // 8027 Z�rich_Switzerland // Hauptsitz Via Canova 16, 6901 Lugano_Switzerland Tel. +41 44 218 10 20 // Fax +41 44 218 10 29 // info@corner.ch // corner.ch Swift CBLUCH2280A // Clearing 8490 // CHE-105.962.409 IVA\r\n\r\nPrint date 01.03.2025 // Page 1/18\r\n\r\n\faeouiAEOUI\r\n\r\naeouiAEOUI\r\n\r\nAsset Allocation\r\nLiquidity Cash accounts Money Market Fixed deposits and fiduciaries\r\nBonds Bonds Bond funds / certificates Convertibles\r\nEquities Equities Equity funds/certificates\r\nMixed funds\r\nStructured products Structured products (Bonds) Structured products (Equities) Various Certificates\r\nMetal accounts and precious metals Metal accounts Precious metals\r\nReal Estate\r\nOther assets Hedge Funds & Private Equity Alternative UCITS Commodity funds Options\r\nTotal assets\r\nPortfolio Total\r\n\r\nCountervalue USD 47'850 47'850\r\n11'558'957 10'211'442\r\n1'347'515\r\n27'406 27'406\r\n7'850'257 6'112'507 1'737'750\r\n\r\nWeight 0.25% 0.25%\r\n59.24% 52.34%\r\n6.91%\r\n\r\nLiabilities and obligations\r\nLiabilities Cash accounts Fixed advance\r\nProfit & loss FRA / IRS Futures Fx Forwards\r\n\r\n0.14% 0.14%\r\n\r\n40.24% 31.33%\r\n8.91%\r\n\r\nMESSOS ENTERPRISES LTD.\r\nValuation as of 28.02.2025 Client Number 366223\r\nAssets and Liabilities Structure\r\nCountervalue USD\r\n\r\n26'129 26'129\r\n\r\n0.13% 0.13%\r\n\r\n19'510'599\r\n\r\n100.00%\r\n\r\nTotal gain/loss of liabilities and obligations\r\n\r\n0\r\n\r\n19'510'599\r\n\r\nCorn�r Banca SA // T�distrasse 27 // Postfach 1640 // 8027 Z�rich_Switzerland // Hauptsitz Via Canova 16, 6901 Lugano_Switzerland Tel. +41 44 218 10 20 // Fax +41 44 218 10 29 // info@corner.ch // corner.ch Swift CBLUCH2280A // Clearing 8490 // CHE-105.962.409 IVA\r\n\r\nPrint date 01.03.2025 // Page 2/18\r\n\r\n\faeouiAEOUI\r\n\r\naeouiAEOUI\r\n\r\nAsset Allocation\r\nLiquidity Cash accounts Money Market Fixed deposits and fiduciaries\r\nBonds Bonds Bond funds / certificates Convertibles\r\nEquities Equities Equity funds/certificates\r\nMixed funds\r\nStructured products Structured products (Bonds) Structured products (Equities) Various Certificates\r\nMetal accounts and precious metals Metal accounts Precious metals\r\nReal Estate\r\nOther assets Hedge Funds & Private Equity Alternative UCITS Commodity funds Options\r\nTotal assets\r\n\r\nCountervalue USD\r\n47'850 47'850\r\n\r\nWeight\r\n0.25% 0.25%\r\n\r\n11'558'957 10'211'442\r\n1'347'515\r\n\r\n59.24% 52.34%\r\n6.91%\r\n\r\n27'406 27'406\r\n\r\n0.14% 0.14%\r\n\r\n7'850'257 6'112'507 1'737'750\r\n\r\n40.24% 31.33%\r\n8.91%\r\n\r\n26'129 26'129\r\n\r\n0.13% 0.13%\r\n\r\n19'510'599 100.00%\r\n\r\nUSD\r\n0.25% 0.25%\r\n\r\nCHF\r\n\r\n59.24% 52.34%\r\n6.91%\r\n0.14% 0.14%\r\n\r\n40.24% 31.33%\r\n8.91%\r\n\r\n0.13% 0.13%\r\n\r\n99.86%\r\n\r\n0.14%\r\n\r\nCorn�r Banca SA // T�distrasse 27 // Postfach 1640 // 8027 Z�rich_Switzerland // Hauptsitz Via Canova 16, 6901 Lugano_Switzerland Tel. +41 44 218 10 20 // Fax +41 44 218 10 29 // info@corner.ch // corner.ch Swift CBLUCH2280A // Clearing 8490 // CHE-105.962.409 IVA\r\n\r\nMESSOS ENTERPRISES LTD.\r\nValuation as of 28.02.2025 Client Number 366223\r\nCurrency allocation\r\nPrint date 01.03.2025 // Page 3/18\r\n\r\n\f01/2024 02/2024 03/2024 04/2024 05/2024 06/2024 07/2024 08/2024 09/2024 10/2024 11/2024 12/2024 01/2025 02/2025 03/2025 04/2025 05/2025 06/2025 07/2025 08/2025 09/2025 10/2025 11/2025 12/2025\r\n\r\naeouiAEOUI\r\n\r\naeouiAEOUI\r\n\r\nEvaluation Period 01.01.2025 // 28.02.2025\r\nValue as of 31.12.2024 Value as of 28.02.2025\r\nInflows/Outflows Money In Money Out Security In Security Out\r\nPerformance TWR Contribution of currencies In Local Currency Thereof Earnings\r\n\r\n8.00% 6.00% 4.00% 2.00% 0.00% -2.00%\r\n\r\n5.56%\r\n\r\n8.00% 6.00% 4.00% 2.00% 0.00% -2.00%\r\n\r\n1.76%\r\n\r\nPerformance 2024\r\nCorn�r Banca SA // T�distrasse 27 // Postfach 1640 // 8027 Z�rich_Switzerland // Hauptsitz Via Canova 16, 6901 Lugano_Switzerland Tel. +41 44 218 10 20 // Fax +41 44 218 10 29 // info@corner.ch // corner.ch Swift CBLUCH2280A // Clearing 8490 // CHE-105.962.409 IVA\r\n\r\nPerformance 2025\r\n\r\nMESSOS ENTERPRISES LTD.\r\nValuation as of 28.02.2025 Client Number 366223\r\nPerformance Overview/Evolution\r\n\r\nUSD\r\n19'172'732 19'510'599\r\n0 0 0 0 0\r\n337'865 74\r\n337'791 69'055\r\n\r\nin %\r\n1.76% 0.00% 1.76% 0.36%\r\n\r\nPrint date 01.03.2025 // Page 4/18\r\n\r\n\faeouiAEOUI\r\n\r\naeouiAEOUI\r\n\r\nCurrency\r\n\r\nNominal/ Description Quantity\r\n\r\nCash accounts credit\r\n\r\nUSD\r\n\r\n47'849.64 ORDINARY USD Cash Accounts // 366223-CC-0002 IBAN: CH1908490000366223002 PRC: 1.00\r\n\r\nTotal Liquidity thereof Cash accounts\r\n\r\nAverage Acquisition price Average Acquisition FX Rate\r\n\r\nActual Price Actual Ex. Rate\r\nPrice Date\r\n\r\nPerf YTD\r\n\r\nMESSOS ENTERPRISES LTD.\r\nValuation as of 28.02.2025 Client Number 366223\r\n\r\nLiquidity and liabilities\r\n\r\nPerf Total Perf Market Perf Currency\r\n\r\nValuation in price currency Thereof accruals\r\nCountervalue USD\r\n\r\nin % of assets\r\n\r\n47'850\r\n\r\n0.25%\r\n\r\nUSD USD\r\n\r\n47'850 47'850\r\n\r\n0.25% 0.25%\r\n\r\nCorn�r Banca SA // T�distrasse 27 // Postfach 1640 // 8027 Z�rich_Switzerland // Hauptsitz Via Canova 16, 6901 Lugano_Switzerland Tel. +41 44 218 10 20 // Fax +41 44 218 10 29 // info@corner.ch // corner.ch Swift CBLUCH2280A // Clearing 8490 // CHE-105.962.409 IVA\r\n\r\nPrint date 01.03.2025 // Page 5/18\r\n\r\n\faeouiAEOUI\r\n\r\naeouiAEOUI\r\n\r\nCurrency\r\n\r\nNominal/ Description Quantity\r\n\r\nAverage Acquisition price Average Acquisition FX Rate\r\n\r\nBonds, Bond funds, Convertible bonds, Interest options\r\n\r\nUSD\r\n\r\n200'000 TORONTO DOMINION BANK NOTES 23-23.02.27 REG-S VRN ISIN: XS2530201644 // Valorn.: 125350273 Ordinary Bonds // Maturity: 23.02.2027 Coupon: 23.5 // Quarterly 3.32% // Days: 7 Moody's: A2 // PRC: 2.00\r\n\r\nUSD\r\n\r\n200'000 CANADIAN IMPERIAL BANK OF COMMERCE NOTES 23-22.08.28 VRN ISIN: XS2588105036 // Valorn.: 112286204 Ordinary Bonds // Maturity: 22.02.2028 Coupon: 23.2 // Annual 5.1531% // Days: 8 PRC: 4.00\r\n\r\nUSD\r\n\r\n1'500'000 HARP ISSUER (4% MIN/5,5% MAX) NOTES 2023-18.09.2028 SE.195 ISIN: XS2665592833 // Valorn.: 128829182 Ordinary Bonds // Maturity: 18.09.2028 Coupon: 18.9 // Annual 4% // Days: 162 PRC: 4.00\r\n\r\nUSD\r\n\r\n690'000 GOLDMAN SACHS 0% NOTES 23-07.11.29 SERIES P ISIN: XS2692298537 // Valorn.: 129157183 Ordinary Bonds // Maturity: 07.11.2029 YTM: -1.35 // PRC: 4.00\r\n\r\nUSD\r\n\r\n100'000 LUMINIS (4.2 % MIN/5.5 % MAX) NOTES 2024-17.01.30 ISIN: XS2754416860 // Valorn.: 132648671 Ordinary Bonds // Maturity: 17.01.2030 Coupon: 17.1 // Annual 5.238% // Days: 42 PRC: 4.00\r\n\r\nUSD\r\n\r\n100'000 CIBC 0% NOTES 2024-13.02.2030 VARIABLE RATE ISIN: XS2761230684 // Valorn.: 112288215 Zero Bonds // Maturity: 13.02.2030 Coupon: 13.2 // Annual 2% // Days: 17 // YTM: 6.91 PRC: 4.00\r\n\r\nUSD\r\n\r\n250'000 BANK OF AMERICA NOTES 2023-20.12.31 VARIABLE RATE ISIN: XS2736388732 // Valorn.: 131799640 Ordinary Bonds // Maturity: 20.12.2031 Days: 265 PRC: 4.00\r\n\r\n100.2000 100.2000\r\n99.0990 100.1000 100.2000 100.2000 100.2000\r\n\r\nActual Price Actual Ex. Rate\r\nPrice Date\r\n99.3080 28.02.2025\r\n99.5002 27.02.2025\r\n98.3900 28.02.2025\r\n106.5700 28.02.2025\r\n97.6600 28.02.2025\r\n101.7291 27.02.2025\r\n98.6200 28.02.2025\r\n\r\nPerf YTD\r\n\r\nPerf Total Perf Market Perf Currency\r\n\r\nMESSOS ENTERPRISES LTD.\r\nValuation as of 28.02.2025 Client Number 366223\r\n\r\nBonds\r\n\r\nValuation in price currency Thereof accruals\r\nCountervalue USD\r\n\r\nin % of assets\r\n\r\n0.36%\r\n\r\n-0.89%\r\n\r\n198'745 129\r\n\r\n1.02%\r\n\r\n0.34%\r\n\r\n-0.70%\r\n\r\n199'172 172\r\n\r\n1.02%\r\n\r\n1.51%\r\n\r\n-0.72%\r\n\r\n1'502'850 27'000\r\n\r\n7.70%\r\n\r\n1.92% 1.70%\r\n\r\n6.46% -2.53%\r\n\r\n1.73%\r\n\r\n1.53%\r\n\r\n-3.20%\r\n\r\n-1.58%\r\n\r\n735'333\r\n\r\n3.77%\r\n\r\n98'271 611\r\n\r\n0.50%\r\n\r\n101'823 94\r\n\r\n0.52%\r\n\r\n255'383 8'833\r\n\r\n1.31%\r\n\r\nCorn�r Banca SA // T�distrasse 27 // Postfach 1640 // 8027 Z�rich_Switzerland // Hauptsitz Via Canova 16, 6901 Lugano_Switzerland Tel. +41 44 218 10 20 // Fax +41 44 218 10 29 // info@corner.ch // corner.ch Swift CBLUCH2280A // Clearing 8490 // CHE-105.962.409 IVA\r\n\r\nPrint date 01.03.2025 // Page 6/18\r\n\r\n\faeouiAEOUI\r\n\r\naeouiAEOUI\r\n\r\nCurrency\r\n\r\nNominal/ Description Quantity\r\n\r\nAverage Acquisition price Average Acquisition FX Rate\r\n\r\nBonds, Bond funds, Convertible bonds, Interest options\r\n\r\nUSD\r\n\r\n50'000 CITIGROUP GLBL 5.65 % CALL FIXED RATE NOTES 202409.05.34 ISIN: XS2782869916 // Valorn.: 132544344 Ordinary Bonds // Maturity: 09.05.2034 PRC: 4.00 Price to be verified\r\n\r\nUSD\r\n\r\n440'000 BOFA 5.6% 2024-29.05.34 REGS ISIN: XS2824054402 // Valorn.: 135337661 Ordinary Bonds // Callable: 29.05.2026 Coupon: 29.5 // Annual 5.6% // Days: 271 // YTM: 5.08 PRC: 4.00\r\n\r\nUSD\r\n\r\n2'450'000 GS 10Y CALLABLE NOTE 2024-18.06.2034 ISIN: XS2567543397 // Valorn.: 134736192 Ordinary Bonds // Callable: 18.06.2026 Coupon: 18.6 // Annual 5.61% // Days: 252 // YTM: 5.52 PRC: 4.00\r\n\r\nUSD\r\n\r\n1'100'000 CITIGROUP 0% MTN 2024-09.07.34 REGS ISIN: XS2110079584 // Valorn.: 136429245 Zero Bonds // Callable: 09.07.2026 YTM: 5.76 // PRC: 4.00\r\n\r\nUSD\r\n\r\n90'000 CITIGROUP GLBL 0 % MEDIUM TERM NOTES 2024-01.08.34 GLOBAL RE ISIN: XS2848820754 // Valorn.: 135116008 Zero Bonds // Maturity: 01.08.2034 PRC: 4.00\r\n\r\nUSD\r\n\r\n100'000 GOLDMAN SACHS EMTN 2024-30.09.2024 ISIN: XS2829712830 // Valorn.: 134735316 Ordinary Bonds // Maturity: 30.09.2034 YTM: 5.51 // PRC: 4.00\r\n\r\nUSD\r\n\r\n200'000 BANK OF AMERICA 0% NOTES 2024-17.10.2034 ISIN: XS2912278723 // Valorn.: 138689613 Zero Bonds // Maturity: 17.10.2034 YTM: 4.86 // PRC: 4.00\r\n\r\nUSD\r\n\r\n100'000 JPMORGAN CHASE 0 % NOTES 2024-29.10.34 SERIES 202137954 ISIN: XS2381723902 // Valorn.: 128883231 Zero Bonds // Maturity: 29.10.2034 PRC: 4.00\r\n\r\n100.2000\r\n100.2000 100.1000 100.1000 100.2000\r\n99.9996 100.2000 100.2000\r\n\r\nActual Price Actual Ex. Rate\r\nPrice Date\r\n97.5160 28.02.2025\r\n103.7200 28.02.2025\r\n100.5900 27.02.2025\r\n100.6700 28.02.2025\r\n99.9500 28.02.2025\r\n93.0200 27.02.2025\r\n98.7771 27.02.2025\r\n96.8496 28.02.2025\r\n\r\nPerf YTD\r\n\r\nPerf Total Perf Market Perf Currency\r\n\r\nMESSOS ENTERPRISES LTD.\r\nValuation as of 28.02.2025 Client Number 366223\r\n\r\nBonds\r\n\r\nValuation in price currency Thereof accruals\r\nCountervalue USD\r\n\r\nin % of assets\r\n\r\n1.26%\r\n\r\n-2.68%\r\n\r\n48'758\r\n\r\n0.25%\r\n\r\n1.55%\r\n\r\n3.51%\r\n\r\n1.33%\r\n\r\n0.49%\r\n\r\n2.08% 2.24%\r\n\r\n0.57% -0.25%\r\n\r\n1.93% 1.11% 1.92%\r\n\r\n-6.98% -1.42% -3.34%\r\n\r\n474'916 18'548\r\n\r\n2.43%\r\n\r\n2'560'667 96'212\r\n\r\n13.12%\r\n\r\n1'107'370\r\n\r\n5.68%\r\n\r\n89'955\r\n\r\n0.46%\r\n\r\n93'020\r\n\r\n0.48%\r\n\r\n197'554\r\n\r\n1.01%\r\n\r\n96'850\r\n\r\n0.50%\r\n\r\nCorn�r Banca SA // T�distrasse 27 // Postfach 1640 // 8027 Z�rich_Switzerland // Hauptsitz Via Canova 16, 6901 Lugano_Switzerland Tel. +41 44 218 10 20 // Fax +41 44 218 10 29 // info@corner.ch // corner.ch Swift CBLUCH2280A // Clearing 8490 // CHE-105.962.409 IVA\r\n\r\nPrint date 01.03.2025 // Page 7/18\r\n\r\n\faeouiAEOUI\r\n\r\naeouiAEOUI\r\n\r\nCurrency\r\n\r\nNominal/ Description Quantity\r\n\r\nAverage Acquisition price Average Acquisition FX Rate\r\n\r\nBonds, Bond funds, Convertible bonds, Interest options\r\n\r\nUSD\r\n\r\n250'000 GOLDMAN SACHS 0% EURO MEDIUM TERM NOTES 202418.11.2034 ISIN: XS2829752976 // Valorn.: 138874416 Ordinary Bonds // Maturity: 18.11.2034 YTM: 5.49 // PRC: 4.00\r\n\r\nUSD\r\n\r\n150'000 BANK OF AMERICA 0 % NOTES 2024-11.12.34 REG S ISIN: XS2953741100 // Valorn.: 138494467 Zero Bonds // Maturity: 11.12.2034 YTM: 5.13 // PRC: 4.00\r\n\r\nUSD\r\n\r\n500'000 JPMORGAN CHASE 0% NOTES 2024-19.12.2034 ISIN: XS2381717250 // Valorn.: 128883267 Zero Bonds // Maturity: 19.12.2034 PRC: 4.00\r\n\r\nUSD\r\n\r\n50'000 GOLDMAN SACHS 0% NOTES 2025-03.02.2035 ISIN: XS2481066111 // Valorn.: 126294402 Zero Bonds // Maturity: 03.02.2035 YTM: -0.09 // PRC: 3.69\r\n\r\nUSD\r\n\r\n1'470'000 DEUTSCHE BANK 0 % NOTES 2025-14.02.35 ISIN: XS2964611052 // Valorn.: 141235167 Zero Bonds // Maturity: 14.02.2035 YTM: 5.31 // PRC: 4.00\r\n\r\nUSD\r\n\r\n2'581.79 PREMIUM ALT.S.A. SICAV-SIF - COMMERCIAL FINANCE OPP.XB SP ISIN: LU2228214107 // Valorn.: 57282891 Bond Funds / Certificates PRC: 4.00\r\n\r\nUSD\r\n\r\n350'000 BK JULIUS BAER CAP.PROT.(3,25% MIN.4,5% MAX)23-26.05.28 VRN ISIN: CH1269060229 // Valorn.: 126906022 Structured Bonds // Maturity: 26.05.2028 Coupon: 26.5 // Quarterly 3.25% // Days: 2 PRC: 3.00 Price to be verified\r\n\r\nUSD\r\n\r\n690'000 DEUTSCHE BANK NOTES 23-08.11.28 VRN ISIN: XS0461497009 // Valorn.: 130269069 Ordinary Bonds // Maturity: 08.11.2028 Coupon: 8.11 // Annual 5.5% // Days: 112 PRC: 4.00\r\n\r\n99.6790 99.1980 100.2000 100.1000 100.0000 81.5304 100.6237\r\n100.1000\r\n\r\nActual Price Actual Ex. Rate\r\nPrice Date\r\n97.8700 27.02.2025\r\n98.7200 27.02.2025\r\n103.8400 26.02.2025\r\n100.8900 28.02.2025\r\n101.2500 27.02.2025\r\n44.7800 13.09.2024\r\n97.4500 28.02.2025\r\n100.2700 27.02.2025\r\n\r\nPerf YTD\r\n\r\nPerf Total Perf Market Perf Currency\r\n\r\nMESSOS ENTERPRISES LTD.\r\nValuation as of 28.02.2025 Client Number 366223\r\n\r\nBonds\r\n\r\nValuation in price currency Thereof accruals\r\nCountervalue USD\r\n\r\nin % of assets\r\n\r\n1.81%\r\n\r\n-1.81%\r\n\r\n244'675\r\n\r\n1.25%\r\n\r\n2.91%\r\n\r\n-0.48%\r\n\r\n6.51%\r\n\r\n3.63%\r\n\r\n0.79%\r\n\r\n0.79%\r\n\r\n1.25%\r\n\r\n1.25%\r\n\r\n0.00%\r\n\r\n-45.08%\r\n\r\n148'080\r\n\r\n0.76%\r\n\r\n519'200\r\n\r\n2.66%\r\n\r\n50'445\r\n\r\n0.26%\r\n\r\n1'488'375\r\n\r\n7.63%\r\n\r\n115'613\r\n\r\n0.59%\r\n\r\n0.98%\r\n\r\n-3.15%\r\n\r\n341'138 63\r\n\r\n1.75%\r\n\r\n0.92%\r\n\r\n0.17%\r\n\r\n703'670 11'807\r\n\r\n3.61%\r\n\r\nCorn�r Banca SA // T�distrasse 27 // Postfach 1640 // 8027 Z�rich_Switzerland // Hauptsitz Via Canova 16, 6901 Lugano_Switzerland Tel. +41 44 218 10 20 // Fax +41 44 218 10 29 // info@corner.ch // corner.ch Swift CBLUCH2280A // Clearing 8490 // CHE-105.962.409 IVA\r\n\r\nPrint date 01.03.2025 // Page 8/18\r\n\r\n\faeouiAEOUI\r\n\r\naeouiAEOUI\r\n\r\nCurrency\r\n\r\nNominal/ Description Quantity\r\n\r\nAverage Acquisition price Average Acquisition FX Rate\r\n\r\nBonds, Bond funds, Convertible bonds, Interest options\r\n\r\nUSD\r\n\r\n140'000 SOCIETE GENERALE 32.46 % NOTES 2024-01.03.30 REG S ISIN: XS2746319610 // Valorn.: 133393503 Ordinary Bonds // Maturity: 01.03.2030 Coupon: Annual 32.46% // Days: 353 // YTM: 17.08 PRC: 4.00\r\n\r\n100.2000\r\n\r\nActual Price Actual Ex. Rate\r\nPrice Date\r\n101.8100 28.02.2025\r\n\r\nTotal Bonds Accrued interest thereof Bonds thereof Bond funds / certficates\r\n\r\nPerf YTD\r\n\r\nPerf Total Perf Market Perf Currency\r\n\r\nMESSOS ENTERPRISES LTD.\r\nValuation as of 28.02.2025 Client Number 366223\r\n\r\nBonds\r\n\r\nValuation in price currency Thereof accruals\r\nCountervalue USD\r\n\r\nin % of assets\r\n\r\n2.40%\r\n\r\n1.61%\r\n\r\n187'094 44'560\r\n\r\n0.96%\r\n\r\nUSD USD USD USD\r\n\r\n11'558'957 208'029\r\n10'211'442 1'347'515\r\n\r\n59.24% 52.34%\r\n6.91%\r\n\r\nCorn�r Banca SA // T�distrasse 27 // Postfach 1640 // 8027 Z�rich_Switzerland // Hauptsitz Via Canova 16, 6901 Lugano_Switzerland Tel. +41 44 218 10 20 // Fax +41 44 218 10 29 // info@corner.ch // corner.ch Swift CBLUCH2280A // Clearing 8490 // CHE-105.962.409 IVA\r\n\r\nPrint date 01.03.2025 // Page 9/18\r\n\r\n\faeouiAEOUI\r\n\r\naeouiAEOUI\r\n\r\nCurrency\r\n\r\nNominal/ Description Quantity\r\n\r\nEquities, Equity funds, Options on equities/indices\r\n\r\nCHF\r\n\r\n800 UBS GROUP INC NAMEN-AKT. ISIN: CH0244767585 // Valorn.: 24476758 Ordinary Stocks // PRC: 3.35\r\n\r\nTotal Equities thereof Equities (without options)\r\n\r\nAverage Acquisition price Average Acquisition FX Rate\r\n\r\nActual Price Actual Ex. Rate\r\nPrice Date\r\n\r\nPerf YTD\r\n\r\nPerf Total Perf Market Perf Currency\r\n\r\nMESSOS ENTERPRISES LTD.\r\nValuation as of 28.02.2025 Client Number 366223\r\n\r\nEquities\r\n\r\nValuation in price currency Thereof accruals\r\nCountervalue USD\r\n\r\nin % of assets\r\n\r\n221.5641 1.1340\r\n\r\n30.9000 1.1086\r\n28.02.2025\r\n\r\n11.43%\r\n\r\n-86.37% -86.05%\r\n-2.24%\r\nUSD USD\r\n\r\n24'720 27'406\r\n27'406 27'406\r\n\r\n0.14%\r\n0.14% 0.14%\r\n\r\nCorn�r Banca SA // T�distrasse 27 // Postfach 1640 // 8027 Z�rich_Switzerland // Hauptsitz Via Canova 16, 6901 Lugano_Switzerland Tel. +41 44 218 10 20 // Fax +41 44 218 10 29 // info@corner.ch // corner.ch Swift CBLUCH2280A // Clearing 8490 // CHE-105.962.409 IVA\r\n\r\nPrint date 01.03.2025 // Page 10/18\r\n\r\n\faeouiAEOUI\r\n\r\naeouiAEOUI\r\n\r\nCurrency\r\n\r\nNominal/ Description Quantity\r\n\r\nAverage Acquisition price Average Acquisition FX Rate\r\n\r\nStructured products (Bonds)\r\n\r\nUSD\r\n\r\n200'000 BCO SAFRA CAYMAN 5% STRUCT.NOTE 2022-21.06.27 3,4% CITD 26 ISIN: XS2519369867 // Valorn.: 121050656 Other convertible bonds // Maturity: 21.06.2027 Days: 69 // PRC: 5.00\r\n\r\nUSD\r\n\r\n500'000 BNP PARIBAS ISS STRUCT.NOTE 21-08.01.29 ON DBDK 29 631 ISIN: XS2315191069 // Valorn.: 111918998 Structured Bonds // Maturity: 08.01.2029 Days: 52 // PRC: 5.00 Price to be verified\r\n\r\nUSD\r\n\r\n1'200'000 CITIGROUP ISIN: XS2792098779 // Valorn.: 140288136 Structured Bonds // Maturity: 02.12.2034 // PRC: 5.00 Price to be verified\r\n\r\nUSD\r\n\r\n690'000 EMERALD BAY NOTES 23-17.09.29 S.2023-05 REG-S VRN WELLS F. ISIN: XS2714429128 // Valorn.: 130738882 Structured Bonds // Maturity: 17.09.2029 Days: 164 // PRC: 5.00 Price to be verified\r\n\r\nUSD\r\n\r\n500'000 GOLDMAN SACHS GR.STRUCT.NOTE 21-20.12.28 VRN ON NAT 34 ISIN: XS2105981117 // Valorn.: 114118068 Structured Bonds // Maturity: 20.12.2028 Days: 70 // PRC: 5.00 Price to be verified\r\n\r\nUSD\r\n\r\n1'600'000 LUMINIS 5.7% STR NOTE 2024-26.04.33 WFC 24W ISIN: XS2838389430 // Valorn.: 135968317 Structured Bonds // Maturity: 26.04.2033 Days: 249 // PRC: 5.00 Price to be verified\r\n\r\nUSD\r\n\r\n500'000 LUMINIS REPACK NOTES 23-25.05.29 VRN ON 4,625%\r\n\r\nRABOBANK 29\r\n\r\nISIN: XS2631782468 // Valorn.: 127708275\r\n\r\nStructured Bonds // Maturity: 25.05.2029\r\n\r\nDays: 19 // PRC: 5.00\r\n\r\nPrice to be verified\r\n\r\nUnderlying:\r\n\r\nFED RES BK SOFR US\r\n\r\n100.7288 100.5241 100.0000 100.4462 100.5243 100.1000\r\n98.0181\r\n\r\nActual Price Actual Ex. Rate\r\nPrice Date\r\n97.9853 28.02.2025\r\n98.7000 28.02.2025\r\n98.0650 28.02.2025\r\n102.6130 28.02.2025\r\n97.8400 28.02.2025\r\n97.5300 28.02.2025\r\n98.0600 28.02.2025\r\n\r\nPerf YTD\r\n\r\nPerf Total Perf Market Perf Currency\r\n\r\nMESSOS ENTERPRISES LTD.\r\nValuation as of 28.02.2025 Client Number 366223\r\n\r\nStructured products\r\n\r\nValuation in price currency Thereof accruals\r\nCountervalue USD\r\n\r\nin % of assets\r\n\r\n-2.01%\r\n\r\n-2.72%\r\n\r\n197'888 1'917\r\n\r\n1.01%\r\n\r\n-0.08%\r\n\r\n-1.81%\r\n\r\n498'133 4'633\r\n\r\n2.55%\r\n\r\n0.08%\r\n\r\n-1.94%\r\n\r\n1'176'780\r\n\r\n6.03%\r\n\r\n1.55%\r\n\r\n2.16%\r\n\r\n725'139 17'109\r\n\r\n3.72%\r\n\r\n0.93%\r\n\r\n-2.67%\r\n\r\n494'914 5'714\r\n\r\n2.54%\r\n\r\n0.82%\r\n\r\n-2.57%\r\n\r\n0.86%\r\n\r\n0.04%\r\n\r\n1'623'560 63'080\r\n\r\n8.32%\r\n\r\n491'716 1'416\r\n\r\n2.52%\r\n\r\nCorn�r Banca SA // T�distrasse 27 // Postfach 1640 // 8027 Z�rich_Switzerland // Hauptsitz Via Canova 16, 6901 Lugano_Switzerland Tel. +41 44 218 10 20 // Fax +41 44 218 10 29 // info@corner.ch // corner.ch Swift CBLUCH2280A // Clearing 8490 // CHE-105.962.409 IVA\r\n\r\nPrint date 01.03.2025 // Page 11/18\r\n\r\n\faeouiAEOUI\r\n\r\naeouiAEOUI\r\n\r\nCurrency\r\n\r\nNominal/ Description Quantity\r\n\r\nAverage Acquisition price Average Acquisition FX Rate\r\n\r\nStructured products (Bonds)\r\n\r\nUSD\r\n\r\n100'000 NATIXIS STRUC.NOTES 19-20.6.26 VRN ON 4,75%METLIFE 21 SRN ISIN: XS1700087403 // Valorn.: 39877135 Structured Bonds // Maturity: 20.06.2026 // PRC: 5.00 Price to be verified\r\n\r\nUSD\r\n\r\n200'000 NOVUS CAPITAL CREDIT LINKED NOTES 2023-27.09.2029 ISIN: XS2594173093 // Valorn.: 125443809 Structured Bonds // Maturity: 27.09.2029 Days: 3 // PRC: 5.00 Price to be verified\r\n\r\nUSD\r\n\r\n500'000 NOVUS CAPITAL STRUCT.NOTE 2021-12.01.28 VRN ON NATWEST GROUP ISIN: XS2407295554 // Valorn.: 114718568 Structured Bonds // Maturity: 12.01.2028 Days: 48 // PRC: 5.00 Price to be verified\r\n\r\nUSD\r\n\r\n100'000 RBC TORONTO 5,06% CREDIT LINKED NOTE 2022-20.06.2027 ISIN: XS2518123653 // Valorn.: 121449211 Structured Bonds // Maturity: 20.06.2027 Days: 250 // PRC: 5.00 Price to be verified\r\n\r\n91.0217 99.0592 100.5243 100.9008\r\n\r\nActual Price Actual Ex. Rate\r\nPrice Date\r\n99.7085 28.02.2025\r\n96.4000 28.02.2025\r\n100.8300 28.02.2025\r\n100.1000 24.02.2025\r\n\r\nStructured products (Equities)\r\n\r\nUSD\r\n\r\n1'000'000 NOVUS CAPITAL STRUCTURED NOTES 20-15.05.26 ON CS\r\n\r\nGROUP\r\n\r\nISIN: XS2252299883 // Valorn.: 58001077\r\n\r\nStructured products equity // Maturity: 15.05.2026 // PRC: 5.00\r\n\r\nPrice to be verified\r\n\r\nUnderlying:\r\n\r\nINTERBK LIBOR 3 MTH\r\n\r\nUSD\r\n\r\n500'000 RAIFF 4.5% STRUC NTS 23-11.07.28 ON REF ASSET ISIN: CH1259345242 // Valorn.: 125934524 Structured products equity // Maturity: 11.07.2028 // PRC: 5.00 Price to be verified\r\n\r\n100.3664\r\n\r\n98.7600 28.02.2025\r\n\r\n98.5199\r\n\r\n100.0700 28.02.2025\r\n\r\nPerf YTD\r\n\r\nPerf Total Perf Market Perf Currency\r\n\r\nMESSOS ENTERPRISES LTD.\r\nValuation as of 28.02.2025 Client Number 366223\r\n\r\nStructured products\r\n\r\nValuation in price currency Thereof accruals\r\nCountervalue USD\r\n\r\nin % of assets\r\n\r\n0.98%\r\n\r\n9.54%\r\n\r\n99'709\r\n\r\n0.51%\r\n\r\n-1.70%\r\n\r\n-2.68%\r\n\r\n4.48%\r\n\r\n0.30%\r\n\r\n192'895 95\r\n\r\n0.99%\r\n\r\n508'159 4'009\r\n\r\n2.60%\r\n\r\n0.89%\r\n\r\n-0.79%\r\n\r\n103'614 3'514\r\n\r\n0.53%\r\n\r\n0.38%\r\n\r\n-1.60%\r\n\r\n987'600\r\n\r\n5.06%\r\n\r\n0.93%\r\n\r\n1.57%\r\n\r\n500'350\r\n\r\n2.56%\r\n\r\nCorn�r Banca SA // T�distrasse 27 // Postfach 1640 // 8027 Z�rich_Switzerland // Hauptsitz Via Canova 16, 6901 Lugano_Switzerland Tel. +41 44 218 10 20 // Fax +41 44 218 10 29 // info@corner.ch // corner.ch Swift CBLUCH2280A // Clearing 8490 // CHE-105.962.409 IVA\r\n\r\nPrint date 01.03.2025 // Page 12/18\r\n\r\n\faeouiAEOUI\r\n\r\naeouiAEOUI\r\n\r\nCurrency\r\n\r\nNominal/ Description Quantity\r\n\r\nAverage Acquisition price Average Acquisition FX Rate\r\n\r\nStructured products (Equities)\r\n\r\nUSD\r\n\r\n250'000 RAIFF 4.75% STR.NTS 23-11.07.28 ON REF ASSET ISIN: CH1259344831 // Valorn.: 125934483 Structured products equity // Maturity: 11.07.2028 // PRC: 5.00 Price to be verified\r\n\r\n97.1934\r\n\r\nActual Price Actual Ex. Rate\r\nPrice Date\r\n99.9200 28.02.2025\r\n\r\nTotal Structured products Accrued interest thereof Structured products (Bonds) thereof Structured products (Equities)\r\n\r\nPerf YTD\r\n\r\nPerf Total Perf Market Perf Currency\r\n\r\nMESSOS ENTERPRISES LTD.\r\nValuation as of 28.02.2025 Client Number 366223\r\n\r\nStructured products\r\n\r\nValuation in price currency Thereof accruals\r\nCountervalue USD\r\n\r\nin % of assets\r\n\r\n-0.05%\r\n\r\n2.81%\r\n\r\n249'800\r\n\r\n1.28%\r\n\r\nUSD USD USD USD\r\n\r\n7'850'257 101'487\r\n6'112'507 1'737'750\r\n\r\n40.24% 31.33%\r\n8.91%\r\n\r\nCorn�r Banca SA // T�distrasse 27 // Postfach 1640 // 8027 Z�rich_Switzerland // Hauptsitz Via Canova 16, 6901 Lugano_Switzerland Tel. +41 44 218 10 20 // Fax +41 44 218 10 29 // info@corner.ch // corner.ch Swift CBLUCH2280A // Clearing 8490 // CHE-105.962.409 IVA\r\n\r\nPrint date 01.03.2025 // Page 13/18\r\n\r\n\faeouiAEOUI\r\n\r\naeouiAEOUI\r\n\r\nCurrency\r\n\r\nNominal/ Description Quantity\r\n\r\nAverage Acquisition price Average Acquisition FX Rate\r\n\r\nHedge Funds & Private Equity\r\n\r\nUSD\r\n\r\n204.071 EXIGENT ENHANCED INCOME FUND LTD SHS A SERIES 2019 1 R ISIN: XD0466760473 // Valorn.: 46676047 Hedge Funds & Private Equity // PRC: 5.00 Price to be verified\r\n\r\n1'008.3748\r\n\r\nActual Price Actual Ex. Rate\r\nPrice Date\r\n128.0395 31.12.2023\r\n\r\nTotal Other assets thereof Hedge funds & Private Equity\r\n\r\nPerf YTD\r\n\r\nPerf Total Perf Market Perf Currency\r\n\r\nMESSOS ENTERPRISES LTD.\r\nValuation as of 28.02.2025 Client Number 366223\r\n\r\nOther assets\r\n\r\nValuation in price currency Thereof accruals\r\nCountervalue USD\r\n\r\nin % of assets\r\n\r\n0.00%\r\n\r\n-87.30%\r\n\r\n26'129\r\n\r\n0.13%\r\n\r\nUSD USD\r\n\r\n26'129 26'129\r\n\r\n0.13% 0.13%\r\n\r\nCorn�r Banca SA // T�distrasse 27 // Postfach 1640 // 8027 Z�rich_Switzerland // Hauptsitz Via Canova 16, 6901 Lugano_Switzerland Tel. +41 44 218 10 20 // Fax +41 44 218 10 29 // info@corner.ch // corner.ch Swift CBLUCH2280A // Clearing 8490 // CHE-105.962.409 IVA\r\n\r\nPrint date 01.03.2025 // Page 14/18\r\n\r\n\faeouiAEOUI\r\n\r\naeouiAEOUI\r\n\r\nNext 12 months\r\n\r\nUSD Total USD\r\n\r\nMESSOS ENTERPRISES LTD.\r\nValuation as of 28.02.2025 Client Number 366223\r\nExpected Cash Flows (Overview)\r\n\r\nAt sight 47'850 47'850\r\n\r\n03 2025 9'846 9'846\r\n\r\n04 2025 92'801 92'801\r\n\r\n05 2025 31'960 31'960\r\n\r\n06 2025 145'005 145'005\r\n\r\n07 2025\r\n\r\n08 2025\r\n\r\n09 2025 100'579 100'579\r\n\r\n10 2025\r\n\r\n11 2025 37'950 37'950\r\n\r\n12 2025 2'500 2'500\r\n\r\n01 2026 5'311 5'311\r\n\r\n02 2026 12'306 12'306\r\n\r\nNext years\r\nUSD Total USD\r\n\r\n2025 420'641 420'641\r\n\r\n2026 285'962 285'962\r\n\r\n2027 465'345 465'345\r\n\r\n2028 2'995'285 2'995'285\r\n\r\n2029 2'135'285 2'135'285\r\n\r\nOthers 10'494'166 10'494'166\r\n\r\nTotal in currency 16'796'684 16'796'684\r\n\r\nWeight in % 100.00% 100.00%\r\n\r\nCorn�r Banca SA // T�distrasse 27 // Postfach 1640 // 8027 Z�rich_Switzerland // Hauptsitz Via Canova 16, 6901 Lugano_Switzerland Tel. +41 44 218 10 20 // Fax +41 44 218 10 29 // info@corner.ch // corner.ch Swift CBLUCH2280A // Clearing 8490 // CHE-105.962.409 IVA\r\n\r\nPrint date 01.03.2025 // Page 15/18\r\n\r\n\faeouiAEOUI\r\n\r\naeouiAEOUI\r\n\r\nLiquidity\r\n\r\nBonds\r\n\r\nEquities Mixed Funds Structured Products\r\n\r\nMetal accounts and precious metals Real Estate Other assets\r\n\r\nMESSOS ENTERPRISES LTD.\r\nValuation as of 28.02.2025 Client Number 366223\r\nGlossary\r\nLiquidity consists of assets deposited in current accounts, as well as time deposits, fiduciary and money market investments. Money market products are normally loans in the form of securities or book-entry rights issued for short-term financing purposes, particularly with a maturity of one year or less. This segment consists of investments in bonds. Ordinary bonds consist of fixed-maturity third-party capital, yielding fixed interest payments by the issuer (obligor) at periodic intervals. In most cases, the bonds are redeemed at maturity. In addition to conventional type bonds, this category also includes: convertible bonds with a right to subscribe for shares or hybrid bonds, bond funds and tracker certificates on bonds. Moreover, this category includes derivatives (options and futures) with underlying bonds. The underlying bonds are not counted in the total of the category. This category includes equities, profit-sharing certificates, dividend-right certificates, and equity funds and tracker certificates on equities. Moreover, this category includes derivatives (options and futures) with underlying equities. The underlying equities are not counted in the total of the category. This category includes strategic funds that invest across a variety of asset classes, such as equities, bonds or real estate. Strategic funds, which are used to implement predetermined investment strategies, are often also referred to as asset allocation funds or mixed funds. This category includes structured products sold by an issuer in public offerings or privately. Their redemption value depends on the performance of one or more underlyings. The underlyings that may be used for structured products include investment instruments such as equities, interest rates, indexes, foreign currencies or commodities. According to the model of the SSPA (Swiss Structured Products Association), the most widespread categories include the following product groups: capital protection products, yield enhancement products, participation products (tracker certificates on equities and bonds are included in the category of the underlying in this valuation), leverage products and investment products with additional credit risk This category includes the most commonly traded precious metals such as gold, silver, platinum and palladium. Investments in precious metals may be made directly (by purchasing the physical metal) or holding a metal account. This category includes real estate funds that typically invest in income-earning properties such as multifamily homes or business establishments.\r\nThis category includes: alternative funds (offshore funds and hedge funds), private equity (investments in venture capital financing, primarily for unlisted enterprises), funds that invest in commodities (e.g. mining products) or in physical assets (such as agricultural produce), forex investments.\r\n\r\nCorn�r Banca SA // T�distrasse 27 // Postfach 1640 // 8027 Z�rich_Switzerland // Hauptsitz Via Canova 16, 6901 Lugano_Switzerland Tel. +41 44 218 10 20 // Fax +41 44 218 10 29 // info@corner.ch // corner.ch Swift CBLUCH2280A // Clearing 8490 // CHE-105.962.409 IVA\r\n\r\nPrint date 01.03.2025 // Page 16/18\r\n\r\n\faeouiAEOUI\r\n\r\naeouiAEOUI\r\n\r\nMESSOS ENTERPRISES LTD.\r\nValuation as of 28.02.2025 Client Number 366223\r\nGlossary\r\n\r\nProduct Risk Classifier (PRC) The PRC (Product Risk Classifier) is a risk indicator, provided by third parties, which is based on quantitative models. This provides an indication of the financial risk of the individual investment products and therefore allows comparing the financial risk of financial instruments belonging to various asset categories and classes. This value is calculated by taking into consideration the three basis aspects of an investment product's financial risk: the market risk, credit risk and liquidity risk. The Portfolio Risk Classifer (PRC) is measured on a scale that goes from 1 (very low risk) to 5 (very high risk).\r\nPerformance Performance is the percentage trend in asset value and therefore expresses the return on a securities portfolio over a given period of time. The performance indicator is expressed as \"Total Return\". In fact, the calculation takes not only price gains/losses into account but also interest (including pro rata interest) and dividend payments. The Bank calculates performance using the TWR (Time-Weighted Return) calculation method, which measures the compound rate of return on a portfolio, eliminating the impact of any cash flows made by the investor (deposits or withdrawals). Performance is stated net, i.e. performance net of taxes and of transaction and management fees. The asset valuation reports the information available at the time of preparation of the asset valuation for the relevant valuation date.\r\n\r\nCorn�r Banca SA // T�distrasse 27 // Postfach 1640 // 8027 Z�rich_Switzerland // Hauptsitz Via Canova 16, 6901 Lugano_Switzerland Tel. +41 44 218 10 20 // Fax +41 44 218 10 29 // info@corner.ch // corner.ch Swift CBLUCH2280A // Clearing 8490 // CHE-105.962.409 IVA\r\n\r\nPrint date 01.03.2025 // Page 17/18\r\n\r\n\faeouiAEOUI\r\n\r\naeouiAEOUI\r\n\r\nMESSOS ENTERPRISES LTD.\r\nValuation as of 28.02.2025 Client Number 366223\r\nNotices and other information\r\n\r\nValuations and prices The present valuation is for information purposes only. The valuation of the assets in this statement is based on the prices and exchange rates derived from commonly used information sources in the banking sector that the Bank considers to be reliable. The stated prices and exchange rates are merely indicative and by no means binding on the Bank; they do not necessarily reflect the amounts actually attainable through market trading. Positions marked \"price to be verified\" refer to instruments that are illiquid or for which no price and/or updated price can be obtained from an official source. The data set forth in the asset valuation - even if they refer to the same valuation date but are generated at different times - may differ from one another due to transactions and/or adjustments, particularly value adjustments, that have been recorded in the meantime with a retroactive effect or value date. The Bank in no way guarantees the accuracy or completeness of the present valuation, the information contained herewith or the calculations related to the assets held in custody. The Bank disclaims all liability for any loss or damage connected with use of the valuation and related information. This document is neither designed nor suitable for tax purposes. Any discrepancies or objections shall be reported to the Bank in writing within 30 days. Otherwise, the contents of this document will be deemed accepted.\r\nExcluded information The present asset valuation does not include liabilities from bills of exchange, acceptances and deeds of pledge, documentary credits, trust loans, sureties, guarantees, other forms of contingent liabilities or outstanding transactions.\r\n\r\nYour financial advisor will be happy to answer any questions you may have about the terms and positions set forth in the present statement.\r\n\r\nCorn�r Banca SA // T�distrasse 27 // Postfach 1640 // 8027 Z�rich_Switzerland // Hauptsitz Via Canova 16, 6901 Lugano_Switzerland Tel. +41 44 218 10 20 // Fax +41 44 218 10 29 // info@corner.ch // corner.ch Swift CBLUCH2280A // Clearing 8490 // CHE-105.962.409 IVA\r\n\r\nPrint date 01.03.2025 // Page 18/18\r\n\r\n\f",
  "tables": [],
  "metadata": {
    "title": "messos.pdf",
    "pages": 0
  },
  "securities": [],
  "financialData": {
    "portfolioInfo": {
      "title": "Valuation as of 28.02.2025\r\nMESSOS ENTERPRISES LTD.",
      "date": "28.02.2025",
      "totalValue": null,
      "currency": "ves",
      "owner": "Number 366223\r\nIndex\r\n1 2 2 3 4 5 5 6 10 11 14 15 16 18",
      "manager": "will be happy to answer any questions you may have about the terms and positions set forth in the present statement.",
      "accountNumber": "s",
      "custodian": "",
      "benchmark": "es",
      "strategy": ""
    },
    "assetAllocation": {
      "categories": [
        {
          "name": "nd Li",
          "percentage": null,
          "value": null
        },
        {
          "name": "NTERP",
          "percentage": null,
          "value": null
        },
        {
          "name": "n as",
          "percentage": null,
          "value": null
        },
        {
          "name": "4 5 5",
          "percentage": 6,
          "value": null
        },
        {
          "name": "anca",
          "percentage": null,
          "value": null
        },
        {
          "name": "te 01",
          "percentage": 3.2025,
          "value": null
        },
        {
          "name": "OUI",
          "percentage": null,
          "value": null
        },
        {
          "name": "UI",
          "percentage": null,
          "value": null
        },
        {
          "name": "sets",
          "percentage": null,
          "value": null
        },
        {
          "name": "ed pr",
          "percentage": null,
          "value": null
        },
        {
          "name": "CHF",
          "percentage": null,
          "value": null
        },
        {
          "name": "urren",
          "percentage": null,
          "value": null
        },
        {
          "name": "y Bon",
          "percentage": null,
          "value": null
        },
        {
          "name": "y Bon",
          "percentage": null,
          "value": null
        },
        {
          "name": "ereof",
          "percentage": null,
          "value": null
        },
        {
          "name": "d Acc",
          "percentage": null,
          "value": null
        },
        {
          "name": "NTERP",
          "percentage": null,
          "value": null
        },
        {
          "name": "n as",
          "percentage": null,
          "value": null
        }
      ],
      "total": 0
    },
    "securities": {},
    "performance": {
      "ytd": null,
      "oneMonth": null,
      "threeMonth": null,
      "sixMonth": null,
      "oneYear": null,
      "threeYear": null,
      "fiveYear": null,
      "tenYear": null,
      "sinceInception": null
    }
  }
}